fastcloudflare/__init__.py
fastcloudflare/api_cfg.py
fastcloudflare/cloudflare_api.py
fastcloudflare/gateway.py
fastcloudflare-0.1.21.dist-info/LICENSE
fastcloudflare-0.1.21.dist-info/METADATA
fastcloudflare-0.1.21.dist-info/WHEEL
fastcloudflare-0.1.21.dist-info/RECORD
