Metadata-Version: 2.3
Name: fastcloudflare
Version: 0.1.21
Summary: 
Author: Miles Copeland Luce
Requires-Python: >=3.13,<4.0
Classifier: Programming Language :: Python :: 3
Classifier: Programming Language :: Python :: 3.13
Requires-Dist: fastapi (>=0.116.1,<0.117.0)
Requires-Dist: fastmicroservices (>=0.1.43,<0.2.0)
Requires-Dist: loguru (>=0.7.3,<0.8.0)
Requires-Dist: starlette (>=0.47.2,<0.48.0)
Requires-Dist: toomanyconfigs (>=0.2.83,<0.3.0)
Requires-Dist: toomanyports (>=0.1.1,<0.2.0)
Requires-Dist: toomanysessions (>=0.1.9960,<0.2.0)
Requires-Dist: toomanythreads (>=0.2.73,<0.3.0)
